books_dl.py
books_dl-0.0.11.dist-info/LICENSE
books_dl-0.0.11.dist-info/METADATA
books_dl-0.0.11.dist-info/WHEEL
books_dl-0.0.11.dist-info/entry_points.txt
books_dl-0.0.11.dist-info/top_level.txt
books_dl-0.0.11.dist-info/RECORD
