Metadata-Version: 2.1
Name: books-dl
Version: 0.0.11
Summary: Консольная утилита для загрузки книжек с одного замечательного сайта.
Home-page: https://github.com/Layerex/books-dl
Author: Layerex
Author-email: layerex@dismail.de
Classifier: Development Status :: 6 - Mature
Classifier: Programming Language :: Python :: 3
Classifier: License :: OSI Approved :: GNU General Public License v3 (GPLv3)
Classifier: Operating System :: OS Independent
Classifier: Topic :: Utilities
License-File: LICENSE
Requires-Dist: beautifulsoup4
Requires-Dist: requests
